srt/__init__.py
srt/srt.py
srt/tools/__init__.py
srt/tools/_cli.py
srt/tools/_srt.py
srt/tools/_utils.py
srt/tools/add.py
srt/tools/deduplicate.py
srt/tools/find.py
srt/tools/fixed_timeshift.py
srt/tools/linear_timeshift.py
srt/tools/match.py
srt/tools/mux.py
srt/tools/normalize.py
srt/tools/paste.py
srt/tools/split.py
srt3-1.0.1.dist-info/LICENSE
srt3-1.0.1.dist-info/METADATA
srt3-1.0.1.dist-info/WHEEL
srt3-1.0.1.dist-info/entry_points.txt
srt3-1.0.1.dist-info/top_level.txt
srt3-1.0.1.dist-info/RECORD
