Metadata-Version: 2.1
Name: srt3
Version: 1.0.1
Summary: A simple library for parsing, modifying, and composing SRT files.
Home-page: https://github.com/switchupcb/srt3
Author: SwitchUpCB
License: MIT
Keywords: srt,srt3
Platform: UNKNOWN
Classifier: Development Status :: 5 - Production/Stable
Classifier: Intended Audience :: Developers
Classifier: License :: OSI Approved :: MIT License
Classifier: Operating System :: OS Independent
Classifier: Programming Language :: Python :: 3
Classifier: Programming Language :: Python :: 3.6
Classifier: Programming Language :: Python :: 3.7
Classifier: Programming Language :: Python :: 3.8
Classifier: Programming Language :: Python :: 3.9
Classifier: Topic :: Multimedia :: Video
Classifier: Topic :: Software Development :: Libraries
Classifier: Topic :: Text Processing
Requires-Python: >=3.3
